scikit_learrnn/Linear Models.py
scikit_learrnn/Load dataset.py
scikit_learrnn/Naive Bayesian genarative m.py
scikit_learrnn/Naive Bayesian.py
scikit_learrnn/__init__.py
scikit_learrnn/cluster cross valdaion.py
scikit_learrnn/label encoding and scaling.py
scikit_learrnn/logistic knn decision svm.py
scikit_learrnn/random forest gradient boosting.py
scikit_learrnn-1.1.3.dist-info/licenses/LICENSE
scikit_learrnn-1.1.3.dist-info/METADATA
scikit_learrnn-1.1.3.dist-info/WHEEL
scikit_learrnn-1.1.3.dist-info/top_level.txt
scikit_learrnn-1.1.3.dist-info/RECORD
